JavaKaifaLiqiMyeclipseQuanmianXiangjieBeifengWang/README.md
JavaKaifaLiqiMyeclipseQuanmianXiangjieBeifengWang/__init__.py
JavaKaifaLiqiMyeclipseQuanmianXiangjieBeifengWang/__main__.py
JavaKaifaLiqiMyeclipseQuanmianXiangjieBeifengWang/file.pdf
JavaKaifaLiqiMyeclipseQuanmianXiangjieBeifengWang/index.html
java_kaifa_liqi_myeclipse_quanmian_xiangjie_beifeng_wang-2024.3.2.0.dist-info/METADATA
java_kaifa_liqi_myeclipse_quanmian_xiangjie_beifeng_wang-2024.3.2.0.dist-info/WHEEL
java_kaifa_liqi_myeclipse_quanmian_xiangjie_beifeng_wang-2024.3.2.0.dist-info/entry_points.txt
java_kaifa_liqi_myeclipse_quanmian_xiangjie_beifeng_wang-2024.3.2.0.dist-info/top_level.txt
java_kaifa_liqi_myeclipse_quanmian_xiangjie_beifeng_wang-2024.3.2.0.dist-info/RECORD
